pycher/__main__.py
pycher/scripts/getallinpath.sh
pycher-0.0.6.dist-info/METADATA
pycher-0.0.6.dist-info/WHEEL
pycher-0.0.6.dist-info/entry_points.txt
pycher-0.0.6.dist-info/top_level.txt
pycher-0.0.6.dist-info/RECORD
