Metadata-Version: 2.1
Name: pycher
Version: 0.0.6
Summary: Quick desktop python launcher
Home-page: https://github.com/ahidalgob/pycher
Author: Augusto Hidalgo
Author-email: ahidalgo94@gmail.com
License: MIT
Platform: UNKNOWN
Classifier: License :: OSI Approved :: MIT License
Classifier: Programming Language :: Python :: 3
Classifier: Programming Language :: Python :: 3.7
